<?xml version="1.0" encoding="UTF-8"?>

<mule xmlns:http="http://www.mulesoft.org/schema/mule/http" xmlns="http://www.mulesoft.org/schema/mule/core"
	xmlns:doc="http://www.mulesoft.org/schema/mule/documentation"
	xmlns:xsi="http://www.w3.org/2001/XMLSchema-instance" xsi:schemaLocation="http://www.mulesoft.org/schema/mule/core http://www.mulesoft.org/schema/mule/core/current/mule.xsd
http://www.mulesoft.org/schema/mule/http http://www.mulesoft.org/schema/mule/http/current/mule-http.xsd">
	<http:listener-config name="HTTP_Listener_config" doc:name="HTTP Listener config" doc:id="5d3419ad-6fc0-4332-9b71-66c22a8169b7" >
		<http:listener-connection host="0.0.0.0" port="8081" />
	</http:listener-config>
	<flow name="gitprojectFlow" doc:id="0bc7be21-3029-43b0-a5c5-d221c8cc4fdf" >
		<http:listener doc:name="Listener" doc:id="6a0f1c66-1ceb-4c3d-908d-5a068648982d" config-ref="HTTP_Listener_config" path="/git"/>
		<logger level="INFO" doc:name="Logger" doc:id="acc46209-12c9-42bc-b38c-5ee22b848cc1" message="sample flow"/>
		<set-payload value="cicd sample project" doc:name="Set Payload" doc:id="6c015dfc-253d-4214-9a0c-aebc8fa4e2a1" />
		<logger level="INFO" doc:name="Logger" doc:id="acc46209-12c9-42bc-b38c-5ee22b848cc1" message="sample flow"/>
	</flow>
</mule>
